twiget_cli.py
twiget/__init__.py
twiget/twiget.py
twiget-0.1.5.dist-info/COPYING
twiget-0.1.5.dist-info/METADATA
twiget-0.1.5.dist-info/WHEEL
twiget-0.1.5.dist-info/entry_points.txt
twiget-0.1.5.dist-info/top_level.txt
twiget-0.1.5.dist-info/RECORD
