Metadata-Version: 2.1
Name: twiget
Version: 0.1.5
Summary: A package for management of filtering queries of the Twitter API
Home-page: https://github.com/aesuli/twiget
Author: Andrea Esuli
Author-email: andrea@esuli.it
License: UNKNOWN
Project-URL: Bug Reports, https://github.com/aesuli/twiget/issues
Project-URL: Source, https://github.com/aesuli/twiget/
Keywords: twitter,retrieval,streams,tweets,search,filter,API
Platform: UNKNOWN
Classifier: Development Status :: 4 - Beta
Classifier: Intended Audience :: Developers
Classifier: Intended Audience :: Science/Research
Classifier: Programming Language :: Python
Classifier: Topic :: Software Development
Classifier: Topic :: Scientific/Engineering
Classifier: License :: OSI Approved :: BSD License
Classifier: Programming Language :: Python :: 3
Classifier: Programming Language :: Python :: 3.6
Classifier: Programming Language :: Python :: 3.7
Classifier: Programming Language :: Python :: 3.8
Classifier: Programming Language :: Python :: 3.9
Classifier: Programming Language :: Python :: 3 :: Only
Requires-Python: >=3.6, <4
License-File: COPYING
Requires-Dist: requests
